actuator_nn/__init__.py
actuator_nn-0.0.0.dist-info/LICENSE
actuator_nn-0.0.0.dist-info/METADATA
actuator_nn-0.0.0.dist-info/WHEEL
actuator_nn-0.0.0.dist-info/top_level.txt
actuator_nn-0.0.0.dist-info/RECORD
